<?xml version="1.0" encoding="UTF-8"?>
<feature
      id="JGroups_feature"
      label="JGroups_feature"
      version="1.0.0.qualifier">

   <description url="http://www.example.com/description">
      JGroups feature. Embarked in it 3 springsource bundles to integrate osgi framework.
   </description>

   <copyright url="http://www.example.com/copyright">
      [Enter Copyright Description here.]
   </copyright>

   <license url="http://www.example.com/license">
      [Enter License Description here.]
   </license>

   <requires>
      <import plugin="org.eclipse.core.runtime" version="3.5.0" match="greaterOrEqual"/>
      <import plugin="org.apache.commons.logging" version="1.0.4" match="greaterOrEqual"/>
      <import plugin="com.springsource.bsh" version="2.0.0" match="greaterOrEqual"/>
      <import plugin="com.springsource.javax.jms" version="1.1.0" match="greaterOrEqual"/>
      <import plugin="org.eclipse.osgi"/>
   </requires>

   <plugin
         id="JGroups"
         os="win32"
         download-size="0"
         install-size="0"
         version="2.5.2"/>

</feature>
